{
  "product": "Atlas CLI",
  "company": "MongoDB, Inc.",
  "license": "LICENSE",
  "upgrade-code": "a995cda5-9731-4158-910c-c8d15371dbda",
  "files": {
    "guid": "ad7bb4a1-9026-4578-8dff-400d66a02a51",
    "items": [
      "bin/atlas.exe"
    ]
  },
  "env": {
    "guid": "94faac3d-4478-431c-8497-fba55dcfb249",
    "vars": [
      {
        "name": "PATH",
        "value": "[INSTALLDIR]",
        "permanent": "yes",
        "system": "no",
        "action": "set",
        "part": "last"
      }
    ]
  },
  "shortcuts": {},
  "choco": {}
}
